wagtail_factories/__init__.py
wagtail_factories/blocks.py
wagtail_factories/builder.py
wagtail_factories/factories.py
wagtail_factories/options.py
wagtail_factories-4.3.0.dist-info/LICENSE
wagtail_factories-4.3.0.dist-info/METADATA
wagtail_factories-4.3.0.dist-info/WHEEL
wagtail_factories-4.3.0.dist-info/top_level.txt
wagtail_factories-4.3.0.dist-info/RECORD
