Metadata-Version: 2.1
Name: wagtail-factories
Version: 4.3.0
Summary: Factory boy classes for wagtail
Home-page: https://github.com/wagtail/wagtail-factories/
Author: Michael van Tellingen
Author-email: michaelvantellingen@gmail.com
License: MIT
Classifier: Development Status :: 5 - Production/Stable
Classifier: License :: OSI Approved :: MIT License
Classifier: Intended Audience :: Developers
Classifier: Operating System :: OS Independent
Classifier: Programming Language :: Python :: 3
Classifier: Programming Language :: Python :: 3.9
Classifier: Programming Language :: Python :: 3.10
Classifier: Programming Language :: Python :: 3.11
Classifier: Programming Language :: Python :: 3.12
Classifier: Programming Language :: Python :: 3.13
Classifier: Programming Language :: Python :: Implementation :: CPython
Classifier: Programming Language :: Python :: Implementation :: PyPy
Classifier: Framework :: Django
Classifier: Framework :: Django :: 4.2
Classifier: Framework :: Django :: 5.1
Classifier: Framework :: Django :: 5.2
Classifier: Framework :: Wagtail
Classifier: Framework :: Wagtail :: 6
Classifier: Framework :: Wagtail :: 7
License-File: LICENSE
Requires-Dist: factory-boy<4,>=3.2
Requires-Dist: wagtail>=6.3
Provides-Extra: docs
Requires-Dist: sphinx>=7.3.7; extra == "docs"
Provides-Extra: test
Requires-Dist: pytest==8.4.1; extra == "test"
Requires-Dist: pytest-django==4.11.1; extra == "test"
Requires-Dist: pytest-cov==6.2.1; extra == "test"
Requires-Dist: coverage==7.10.3; extra == "test"
Requires-Dist: ruff==0.12.8; extra == "test"
